core_etl/__init__.py
core_etl/base.py
core_etl/file_based.py
core_etl/py.typed
core_etl/record_based.py
core_etl-3.0.0.dist-info/METADATA
core_etl-3.0.0.dist-info/WHEEL
core_etl-3.0.0.dist-info/top_level.txt
core_etl-3.0.0.dist-info/RECORD
