Metadata-Version: 2.4
Name: core-etl
Version: 3.0.0
Summary: This project/library contains common elements related to ETL processes...
Author-email: Alejandro Cora González <alek.cora.glez@gmail.com>
Maintainer: Alejandro Cora González
License: MIT
Project-URL: Homepage, https://gitlab.com/bytecode-solutions/core/core-etl
Project-URL: Repository, https://gitlab.com/bytecode-solutions/core/core-etl
Project-URL: Documentation, https://core-etl.readthedocs.io/en/latest/
Project-URL: Issues, https://gitlab.com/bytecode-solutions/core/core-etl/-/issues
Project-URL: Changelog, https://gitlab.com/bytecode-solutions/core/core-etl/-/blob/master/CHANGELOG.md
Classifier: License :: OSI Approved :: MIT License
Classifier: Intended Audience :: Developers
Classifier: Development Status :: 5 - Production/Stable
Classifier: Topic :: Software Development :: Libraries :: Python Modules
Classifier: Topic :: Utilities
Classifier: Programming Language :: Python :: 3
Classifier: Programming Language :: Python :: 3 :: Only
Classifier: Programming Language :: Python :: 3.9
Classifier: Programming Language :: Python :: 3.10
Classifier: Programming Language :: Python :: 3.11
Classifier: Programming Language :: Python :: 3.12
Classifier: Programming Language :: Python :: 3.13
Requires-Python: >=3.9
Requires-Dist: core-mixins>=2.2.0
Requires-Dist: core-tests>=2.0.2
Requires-Dist: typing-extensions>=4.8.0; python_version >= "3.9" and python_version < "3.11"
Provides-Extra: dev
Requires-Dist: core-dev-tools>=1.0.1; extra == "dev"
